qum/__init__.py
qum/compiler.py
qum/database.py
qum/generic_repo.py
qum/query.py
qum/enums/__init__.py
qum/enums/function_type.py
qum/enums/order_type.py
qum/expressions/__init__.py
qum/expressions/expression.py
qum/expressions/function.py
qum/expressions/subquery.py
qum/expressions/table.py
qum/expressions/table_field.py
query_using_methods-0.0.5.dist-info/METADATA
query_using_methods-0.0.5.dist-info/WHEEL
query_using_methods-0.0.5.dist-info/top_level.txt
query_using_methods-0.0.5.dist-info/RECORD
